libdave/__init__.py
libdave-0.0.0a1.dist-info/METADATA
libdave-0.0.0a1.dist-info/WHEEL
libdave-0.0.0a1.dist-info/RECORD
