Metadata-Version: 2.4
Name: libdave
Version: 0.0.0a1
Summary: coming soon
Author-email: arielle <me@arielle.codes>
